{
	"info": {
		"_postman_id": "88390232-76f7-4147-b560-337fbb7977cd",
		"name": "Phu-TODO",
		"schema": "https://schema.getpostman.com/json/collection/v2.1.0/collection.json",
		"_exporter_id": "5083790"
	},
	"item": [
		{
			"name": "TODOs",
			"item": [
				{
					"name": "Get all todos",
					"request": {
						"method": "GET",
						"header": [
							{
								"key": "Authorization",
								"value": "Bearer {{authToken}}",
								"type": "text"
							}
						],
						"url": {
							"raw": "https://{{apiId}}.execute-api.us-east-1.amazonaws.com/dev/todos",
							"protocol": "https",
							"host": [
								"{{apiId}}",
								"execute-api",
								"us-east-1",
								"amazonaws",
								"com"
							],
							"path": [
								"dev",
								"todos"
							]
						}
					},
					"response": []
				},
				{
					"name": "Get todo by Id",
					"request": {
						"method": "GET",
						"header": [
							{
								"key": "Authorization",
								"value": "Bearer {{authToken}}",
								"type": "text"
							}
						],
						"url": {
							"raw": "https://{{apiId}}.execute-api.us-east-1.amazonaws.com/dev/todos/:todoId",
							"protocol": "https",
							"host": [
								"{{apiId}}",
								"execute-api",
								"us-east-1",
								"amazonaws",
								"com"
							],
							"path": [
								"dev",
								"todos",
								":todoId"
							],
							"variable": [
								{
									"key": "todoId",
									"value": "323f28b5-355a-4b98-93f9-67626c1a0c23"
								}
							]
						}
					},
					"response": []
				},
				{
					"name": "Create todo",
					"request": {
						"method": "POST",
						"header": [
							{
								"key": "Content-Type",
								"name": "Content-Type",
								"value": "application/json",
								"type": "text"
							},
							{
								"key": "Authorization",
								"value": "Bearer {{authToken}}",
								"type": "text"
							}
						],
						"body": {
							"mode": "raw",
							"raw": "{\n\t\"name\": \"Water flowers\",\n\t\"dueDate\": \"2019-06-11\"\n}"
						},
						"url": {
							"raw": "https://{{apiId}}.execute-api.us-east-1.amazonaws.com/dev/todos",
							"protocol": "https",
							"host": [
								"{{apiId}}",
								"execute-api",
								"us-east-1",
								"amazonaws",
								"com"
							],
							"path": [
								"dev",
								"todos"
							]
						}
					},
					"response": []
				},
				{
					"name": "Update todo",
					"protocolProfileBehavior": {
						"disabledSystemHeaders": {
							"content-type": true
						}
					},
					"request": {
						"method": "PUT",
						"header": [
							{
								"key": "Content-Type",
								"name": "Content-Type",
								"type": "text",
								"value": "application/json"
							},
							{
								"key": "Authorization",
								"type": "text",
								"value": "Bearer {{authToken}}"
							}
						],
						"body": {
							"mode": "raw",
							"raw": "{\n\t\"name\": \"Phu test\",\n\t\"dueDate\": \"2019-12-11\",\n\t\"done\": true\n}",
							"options": {
								"raw": {
									"language": "json"
								}
							}
						},
						"url": {
							"raw": "https://{{apiId}}.execute-api.us-east-1.amazonaws.com/dev/todos/:todoId",
							"protocol": "https",
							"host": [
								"{{apiId}}",
								"execute-api",
								"us-east-1",
								"amazonaws",
								"com"
							],
							"path": [
								"dev",
								"todos",
								":todoId"
							],
							"variable": [
								{
									"key": "todoId",
									"value": "94646846-9b58-4cfd-8704-85337d132f07"
								}
							]
						}
					},
					"response": []
				},
				{
					"name": "Delete todo",
					"request": {
						"method": "DELETE",
						"header": [
							{
								"key": "Content-Type",
								"name": "Content-Type",
								"type": "text",
								"value": "application/json"
							},
							{
								"key": "Authorization",
								"type": "text",
								"value": "Bearer {{authToken}}"
							}
						],
						"body": {
							"mode": "raw",
							"raw": ""
						},
						"url": {
							"raw": "https://{{apiId}}.execute-api.us-east-1.amazonaws.com/dev/todos/:todoId",
							"protocol": "https",
							"host": [
								"{{apiId}}",
								"execute-api",
								"us-east-1",
								"amazonaws",
								"com"
							],
							"path": [
								"dev",
								"todos",
								":todoId"
							],
							"variable": [
								{
									"key": "todoId",
									"value": "d3a27578-dd58-41be-9bd0-5881af94b27b"
								}
							]
						}
					},
					"response": []
				},
				{
					"name": "Get attachment URL",
					"request": {
						"method": "POST",
						"header": [
							{
								"key": "Authorization",
								"value": "Bearer {{authToken}}",
								"type": "text"
							}
						],
						"body": {
							"mode": "raw",
							"raw": ""
						},
						"url": {
							"raw": "https://{{apiId}}.execute-api.us-east-1.amazonaws.com/dev/todos/:todoId/attachment",
							"protocol": "https",
							"host": [
								"{{apiId}}",
								"execute-api",
								"us-east-1",
								"amazonaws",
								"com"
							],
							"path": [
								"dev",
								"todos",
								":todoId",
								"attachment"
							],
							"variable": [
								{
									"key": "todoId",
									"value": "94646846-9b58-4cfd-8704-85337d132f07"
								}
							]
						}
					},
					"response": []
				}
			],
			"event": [
				{
					"listen": "prerequest",
					"script": {
						"type": "text/javascript",
						"exec": [
							""
						]
					}
				},
				{
					"listen": "test",
					"script": {
						"type": "text/javascript",
						"exec": [
							""
						]
					}
				}
			]
		}
	],
	"event": [
		{
			"listen": "prerequest",
			"script": {
				"type": "text/javascript",
				"exec": [
					""
				]
			}
		},
		{
			"listen": "test",
			"script": {
				"type": "text/javascript",
				"exec": [
					""
				]
			}
		}
	],
	"variable": [
		{
			"key": "apiId",
			"value": "",
			"type": "string"
		},
		{
			"key": "authToken",
			"value": "",
			"type": "string"
		}
	]
}